{"cookies": [], "origins": [{"origin": "https://nikita-filonov.github.io", "localStorage": [{"name": "persist:users", "value": "{\"user\":\"{\\\"id\\\":\\\"60cc4288-94b2-4fb3-8a37-3fc237756f84\\\",\\\"email\\\":\\\"test@mail.ru\\\",\\\"username\\\":\\\"username\\\",\\\"password\\\":\\\"test_password\\\"}\",\"users\":\"[{\\\"id\\\":\\\"60cc4288-94b2-4fb3-8a37-3fc237756f84\\\",\\\"email\\\":\\\"test@mail.ru\\\",\\\"username\\\":\\\"username\\\",\\\"password\\\":\\\"test_password\\\"}]\",\"_persist\":\"{\\\"version\\\":-1,\\\"rehydrated\\\":true}\"}"}, {"name": "persist:courses", "value": "{\"course\":\"{\\\"id\\\":\\\"\\\",\\\"title\\\":\\\"\\\",\\\"userId\\\":\\\"\\\",\\\"maxScore\\\":0,\\\"minScore\\\":0,\\\"exercises\\\":[],\\\"description\\\":\\\"\\\",\\\"previewImage\\\":null,\\\"estimatedTime\\\":\\\"\\\"}\",\"courses\":\"[]\",\"_persist\":\"{\\\"version\\\":-1,\\\"rehydrated\\\":true}\"}"}]}]}